[
{"ID":"ypid:YNEA664979C495D42","Name":"Amazingblingjewelrygroupllc","Address":"2652 Farn Dr, Ellenwood, GA 30294","Featured image":"","Bing Maps URL":"https://www.bing.com/maps?cp=33.61532211303711%7E-84.30361938476562&lvl=16.0&q=Amazingblingjewelrygroupllc%20%2C%202652%20Farn%20Dr%2C%20Ellenwood%2C%20GA%2030294","Latitude":"33.61532211","Longitude":"-84.30361938","Rating":"","Rating Info":"","Category":"Jewelry store","Open Hours":"Open 24 hours","Website":"","Phone":"(404) 839-8988","Emails":"","Social Medias":"","Facebook":"","Instagram":"","Twitter":"","paid":false,"tier":"free","paidAt":null,"paidDays":30,"verified":false,"claimRef":null,"addedAt":"2026-06-15","ratings":[]},
{"ID":"ypid:YN215B256CA05CE634","Name":"Robbin's Demure Pearls","Address":"2776 Rex Rd, Ellenwood, GA 30294","Featured image":"","Bing Maps URL":"https://www.bing.com/maps?cp=33.592647552490234%7E-84.29957580566406&lvl=16.0&q=Robbin's%20Demure%20Pearls%20%2C%202776%20Rex%20Rd%2C%20Ellenwood%2C%20GA%2030294","Latitude":"33.59264755","Longitude":"-84.29957581","Rating":"","Rating Info":"","Category":"Jewelry store","Open Hours":"Closed · Opens tomorrow 10 AM","Website":"http://robbins-demure-pearls.square.site/","Phone":"(770) 742-9328","Emails":"name@cpsymbol.com","Social Medias":"","Facebook":"","Instagram":"","Twitter":"","paid":false,"tier":"free","paidAt":null,"paidDays":30,"verified":false,"claimRef":null,"addedAt":"2026-06-15","ratings":[]},
{"ID":"ypid:YN6DD73744DBFBE7B6","Name":"Giga's Creations","Address":"6036 Cristie Dr, Ellenwood, GA 30294","Featured image":"https://www.bing.com/th?id=OLC.oQnEpvp6nPYSNA480x360&pid=Local","Bing Maps URL":"https://www.bing.com/maps?cp=33.609737396240234%7E-84.28733825683594&lvl=16.0&q=Giga's%20Creations%20%2C%206036%20Cristie%20Dr%2C%20Ellenwood%2C%20GA%2030294","Latitude":"33.6097374","Longitude":"-84.28733826","Rating":"","Rating Info":"","Category":"Jewelry store","Open Hours":"Closed · Opens tomorrow 10 AM","Website":"https://giga-s-creations.ueniweb.com/","Phone":"(678) 887-9031","Emails":"staceycare1436593@gmail.com,legal@ueni.com,abuse@ueni.com,help@ueni.com,help@ueni.om","Social Medias":"https://www.linkedin.com/company/ueni-ltd/,https://www.youtube.com/feed/history?utm_source=pp,https://twitter.com/ueniltd,https://www.facebook.com/ueniltd,https://www.instagram.com/ueni.ltd/,https://www.tiktok.com/@ueni.com","Facebook":"https://www.facebook.com/ueniltd","Instagram":"https://www.instagram.com/ueni.ltd/","Twitter":"https://twitter.com/ueniltd","paid":false,"tier":"free","paidAt":null,"paidDays":30,"verified":false,"claimRef":null,"addedAt":"2026-06-15","ratings":[]}
]
