[
{"ID":"ypid:YN31631F832E70AEFC","Name":"Two Rivers Gun Range","Address":"1006 GA-110, Folkston, GA 31537","Featured image":"https://www.bing.com/th?id=OLC.b3WhIKtl8BiZFA480x360&pid=Local","Bing Maps URL":"https://www.bing.com/maps?cp=30.84478759765625%7E-81.87610626220703&lvl=16.0&q=Two%20Rivers%20Gun%20Range%20%2C%201006%20GA-110%2C%20Folkston%2C%20GA%2031537","Latitude":"30.8447876","Longitude":"-81.87610626","Rating":"","Rating Info":"","Category":"Gun/rifle ranges","Open Hours":"Closes in 18 mins","Website":"https://www.camdencountyga.gov/1098/Two-Rivers-Gun-Range","Phone":"(912) 510-4050","Emails":"","Social Medias":"","Facebook":"","Instagram":"","Twitter":"","paid":false,"tier":"free","paidAt":null,"paidDays":30,"verified":false,"claimRef":null,"addedAt":"2026-06-14","ratings":[]}
]
